pyfb_endpoint/__init__.py
pyfb_endpoint/admin.py
pyfb_endpoint/api.py
pyfb_endpoint/apps.py
pyfb_endpoint/forms.py
pyfb_endpoint/models.py
pyfb_endpoint/serializers.py
pyfb_endpoint/sql_config.py
pyfb_endpoint/urls.py
pyfb_endpoint/validators.py
pyfb_endpoint/views.py
pyfb_endpoint/migrations/0001_initial.py
pyfb_endpoint/migrations/0002_auto_20181218_1700.py
pyfb_endpoint/migrations/0003_auto_20181219_1354.py
pyfb_endpoint/migrations/0004_auto_20181219_1402.py
pyfb_endpoint/migrations/0005_auto_20190130_1417.py
pyfb_endpoint/migrations/0006_auto_20190130_1427.py
pyfb_endpoint/migrations/0007_auto_20190410_1544.py
pyfb_endpoint/migrations/0008_auto_20190410_1547.py
pyfb_endpoint/migrations/0009_auto_20190410_1549.py
pyfb_endpoint/migrations/0010_customerendpoint_domain.py
pyfb_endpoint/migrations/0011_auto_20190523_1729.py
pyfb_endpoint/migrations/0012_auto_20190710_1448.py
pyfb_endpoint/migrations/0013_auto_20190710_1452.py
pyfb_endpoint/migrations/0014_auto_20190710_1456.py
pyfb_endpoint/migrations/0015_providerendpoint_add_plus_in_caller.py
pyfb_endpoint/migrations/__init__.py
pyfb_endpoint/static/css/pyfb_endpoint.css
pyfb_endpoint/static/js/pyfb_endpoint.js
pyfb_endpoint/templates/base.html
pyfb_endpoint/templates/pyfb_endpoint/codec_detail.html
pyfb_endpoint/templates/pyfb_endpoint/codec_form.html
pyfb_endpoint/templates/pyfb_endpoint/codec_list.html
pyfb_endpoint/templates/pyfb_endpoint/customerendpoint_detail.html
pyfb_endpoint/templates/pyfb_endpoint/customerendpoint_form.html
pyfb_endpoint/templates/pyfb_endpoint/customerendpoint_list.html
pyfb_endpoint/templates/pyfb_endpoint/providerendpoint_detail.html
pyfb_endpoint/templates/pyfb_endpoint/providerendpoint_form.html
pyfb_endpoint/templates/pyfb_endpoint/providerendpoint_list.html
pyfb_endpoint-1.1.2.dist-info/DESCRIPTION.rst
pyfb_endpoint-1.1.2.dist-info/METADATA
pyfb_endpoint-1.1.2.dist-info/RECORD
pyfb_endpoint-1.1.2.dist-info/WHEEL
pyfb_endpoint-1.1.2.dist-info/metadata.json
pyfb_endpoint-1.1.2.dist-info/top_level.txt
