Metadata-Version: 2.0
Name: pyfb-endpoint
Version: 1.1.2
Summary: Endpoint app for PyFreeBilling
Home-page: https://www.pyfreebilling.com
Author: Mathias WOLFF
Author-email: mathias@celea.org
License: MIT
Keywords: pyfb-endpoint
Platform: UNKNOWN
Classifier: Development Status :: 5 - Production/Stable
Classifier: Framework :: Django :: 2.2
Classifier: Intended Audience :: Developers
Classifier: License :: OSI Approved :: MIT License
Classifier: Natural Language :: English
Classifier: Programming Language :: Python :: 3.5
Classifier: Programming Language :: Python :: 3.6
Requires-Dist: django-model-utils (>=3.1.2)
Requires-Dist: django-extensions (>=2.1.3)
Requires-Dist: djangorestframework (>=3.9.0)
Requires-Dist: django-crispy-forms (>=1.7.0)
Requires-Dist: pyfb-company (>=0.9.0)
Requires-Dist: pyfb-normalization (>=1.0.0)
Requires-Dist: pyfb-kamailio (>=1.0.0)
Requires-Dist: psycopg2 (>=2.7.4)
Requires-Dist: django-partial-index (>=0.5.2)
Requires-Dist: django-migrate-sql-deux (>=0.2.1)
Requires-Dist: django-autocomplete-light (>=3.3.2)
Requires-Dist: netaddr (>=0.7.19)
